{
  "type": "forge:conditional",
  "recipes": [
    {
      "conditions": [
        {
          "type": "forge:mod_loaded",
          "modid": "tconstruct"
        }
      ],
      "recipe": {
        "type": "tconstruct:melting",
        "byproducts": [
          {
            "amount": 60,
            "fluid": "tconstruct:molten_zinc"
          }
        ],
        "ingredient": {
          "tag": "forge:gems/sphalerite"
        },
        "result": {
          "amount": 180,
          "fluid": "tconstruct:molten_iron"
        },
        "temperature": 800,
        "time": 60
      }
    }
  ]
}